{
  "fields": [
    {
      "name": "event_type",
      "dtype": "VARCHAR_1000"
    },
    {
      "name": "primary_id",
      "dtype": "BIGINT"
    },
    {
      "name": "product_id",
      "dtype": "VARCHAR_1000"
    },
    {
      "name": "quantity",
      "dtype": "BIGINT"
    },
    {
      "name": "user_id",
      "dtype": "BIGINT"
    },
    {
      "name": "session_id",
      "dtype": "VARCHAR_1000"
    },
    {
      "name": "event_type",
      "dtype": "VARCHAR_1000"
    },
    {
      "name": "primary_id",
      "dtype": "BIGINT"
    },
    {
      "name": "user_id",
      "dtype": "BIGINT"
    },
    {
      "name": "session_id",
      "dtype": "VARCHAR_1000"
    },
    {
      "name": "event_type",
      "dtype": "VARCHAR_1000"
    },
    {
      "name": "primary_id",
      "dtype": "BIGINT"
    },
    {
      "name": "product_id",
      "dtype": "VARCHAR_1000"
    },
    {
      "name": "amount",
      "dtype": "DOUBLE"
    },
    {
      "name": "quantity",
      "dtype": "BIGINT"
    },
    {
      "name": "user_id",
      "dtype": "BIGINT"
    },
    {
      "name": "session_id",
      "dtype": "VARCHAR_1000"
    },
    {
      "name": "items",
      "dtype": "VARCHAR_1000"
    },
    {
      "name": "event_type",
      "dtype": "VARCHAR_1000"
    },
    {
      "name": "primary_id",
      "dtype": "BIGINT"
    },
    {
      "name": "user_id",
      "dtype": "BIGINT"
    },
    {
      "name": "session_id",
      "dtype": "VARCHAR_1000"
    },
    {
      "name": "event_type",
      "dtype": "VARCHAR_1000"
    },
    {
      "name": "primary_id",
      "dtype": "BIGINT"
    },
    {
      "name": "page_url",
      "dtype": "VARCHAR_1000"
    },
    {
      "name": "user_id",
      "dtype": "BIGINT"
    },
    {
      "name": "session_id",
      "dtype": "VARCHAR_1000"
    },
    {
      "name": "event_type",
      "dtype": "VARCHAR_1000"
    },
    {
      "name": "primary_id",
      "dtype": "BIGINT"
    },
    {
      "name": "user_id",
      "dtype": "BIGINT"
    },
    {
      "name": "session_id",
      "dtype": "VARCHAR_1000"
    }
  ],
  "mappings": {
    "add_to_cart": [
      "primary_id",
      "quantity",
      "user_id",
      "session_id",
      "product_id"
    ],
    "search": [
      "primary_id",
      "session_id",
      "user_id"
    ],
    "purchase": [
      "primary_id",
      "quantity",
      "user_id",
      "session_id",
      "amount",
      "items",
      "product_id"
    ],
    "login": [
      "primary_id",
      "session_id",
      "user_id"
    ],
    "page_view": [
      "primary_id",
      "user_id",
      "session_id",
      "page_url"
    ],
    "logout": [
      "primary_id",
      "session_id",
      "user_id"
    ]
  }
}